{
  "가": [
    "가/佳",
    "가/加",
    "가/可",
    "가/呿",
    "가/哥",
    "가/哿",
    "가/嘉",
    "가/嘏",
    "가/嫁",
    "가/家",
    "가/暇",
    "가/枷",
    "가/歌",
    "가/珂",
    "가/稼",
    "가/笳",
    "가/舸",
    "가/茄",
    "가/街",
    "가/謌",
    "가/跏",
    "가/軻",
    "가/迦"
  ],
  "각": [
    "각/刻",
    "각/却",
    "각/各",
    "각/埻",
    "각/恪",
    "각/珏",
    "각/脚",
    "각/閣"
  ],
  "간": [
    "간/捍"
  ],
  "갈": [
    "갈/曷"
  ],
  "감": [
    "감/咸",
    "감/玪",
    "감/贛",
    "감/闞",
    "감/黚"
  ],
  "갑": [
    "갑/岬",
    "갑/甲",
    "갑/鉀",
    "갑/閘"
  ],
  "강": [
    "강/剛",
    "강/堈",
    "강/壃",
    "강/姜",
    "강/嫝",
    "강/岡",
    "강/崗",
    "강/康",
    "강/強",
    "강/强",
    "강/彊",
    "강/悾",
    "강/扛",
    "강/橿",
    "강/殭",
    "강/江",
    "강/玒",
    "강/畺",
    "강/疆",
    "강/絳",
    "강/綱",
    "강/罡",
    "강/舡",
    "강/茳",
    "강/講",
    "강/豇",
    "강/跭",
    "강/鋼",
    "강/鎠",
    "강/鏹",
    "강/降",
    "강/頏",
    "강/顜"
  ],
  "개": [
    "개/獬",
    "개/祄",
    "개/豈"
  ],
  "거": [
    "거/呿",
    "거/居",
    "거/巨",
    "거/据",
    "거/據",
    "거/昛",
    "거/炬",
    "거/祛",
    "거/舁",
    "거/蕖",
    "거/裾",
    "거/車",
    "거/鉅"
  ],
  "건": [
    "건/䢖",
    "건/乾",
    "건/件",
    "건/健",
    "건/巾",
    "건/建",
    "건/揵",
    "건/搴",
    "건/湕",
    "건/漧",
    "건/腱",
    "건/虔",
    "건/踺",
    "건/鍵",
    "건/闥",
    "건/鞬"
  ],
  "걸": [
    "걸/傑",
    "걸/杰"
  ],
  "겁": [
    "겁/拾"
  ],
  "견": [
    "견/擐",
    "견/見"
  ],
  "겸": [
    "겸/傔",
    "겸/兼",
    "겸/嗛",
    "겸/岒",
    "겸/槏",
    "겸/玪",
    "겸/縑",
    "겸/謙",
    "겸/鎌",
    "겸/黚"
  ],
  "경": [
    "경/㯳",
    "경/京",
    "경/亰",
    "경/俓",
    "경/倞",
    "경/傾",
    "경/儆",
    "경/冏",
    "경/勁",
    "경/勍",
    "경/卿",
    "경/囧",
    "경/坰",
    "경/境",
    "경/娙",
    "경/嬛",
    "경/巠",
    "경/庚",
    "경/徑",
    "경/慶",
    "경/憬",
    "경/憼",
    "경/扃",
    "경/擎",
    "경/敬",
    "경/景",
    "경/暻",
    "경/曔",
    "경/更",
    "경/檠",
    "경/涇",
    "경/炅",
    "경/烱",
    "경/煢",
    "경/熲",
    "경/燛",
    "경/瑩",
    "경/璄",
    "경/璟",
    "경/璥",
    "경/瓊",
    "경/畊",
    "경/硬",
    "경/磬",
    "경/竟",
    "경/絅",
    "경/經",
    "경/耕",
    "경/耿",
    "경/莖",
    "경/警",
    "경/輕",
    "경/鏡",
    "경/陘",
    "경/頸",
    "경/鶊",
    "경/黥"
  ],
  "계": [
    "계/啓",
    "계/堦",
    "계/堺",
    "계/契",
    "계/季",
    "계/屆",
    "계/悸",
    "계/戒",
    "계/桂",
    "계/械",
    "계/棨",
    "계/溪",
    "계/烓",
    "계/界",
    "계/磎",
    "계/稽",
    "계/系",
    "계/綮",
    "계/縘",
    "계/繫",
    "계/繼",
    "계/誡",
    "계/谿",
    "계/階",
    "계/鷄"
  ],
  "고": [
    "고/叩",
    "고/告",
    "고/固",
    "고/庫",
    "고/撟",
    "고/攷",
    "고/故",
    "고/敲",
    "고/暠",
    "고/杲",
    "고/栲",
    "고/牯",
    "고/皋",
    "고/皐",
    "고/篙",
    "고/羔",
    "고/翺",
    "고/考",
    "고/菰",
    "고/詁",
    "고/誥",
    "고/郜",
    "고/靠",
    "고/顧",
    "고/高",
    "고/鴣",
    "고/鷱",
    "고/鼓",
    "고/鼔"
  ],
  "곤": [
    "곤/坤",
    "곤/堃",
    "곤/崐",
    "곤/崑",
    "곤/悃",
    "곤/昆",
    "곤/梱",
    "곤/琨",
    "곤/緄",
    "곤/衮",
    "곤/袞",
    "곤/裍",
    "곤/錕",
    "곤/鯤",
    "곤/鵾",
    "곤/鶤",
    "곤/齫"
  ],
  "골": [
    "골/汩"
  ],
  "공": [
    "공/供",
    "공/公",
    "공/共",
    "공/功",
    "공/崆",
    "공/工",
    "공/恭",
    "공/悾",
    "공/控",
    "공/攻",
    "공/栱",
    "공/槓",
    "공/珙",
    "공/空",
    "공/箜",
    "공/貢",
    "공/贛",
    "공/鞏",
    "공/龔"
  ],
  "곽": [
    "곽/廓",
    "곽/槨",
    "곽/郭",
    "곽/霍"
  ],
  "관": [
    "관/丱",
    "관/串",
    "관/冠",
    "관/官",
    "관/寛",
    "관/寬",
    "관/慣",
    "관/擐",
    "관/款",
    "관/灌",
    "관/爟",
    "관/琯",
    "관/瓘",
    "관/窾",
    "관/筦",
    "관/管",
    "관/綰",
    "관/罐",
    "관/舘",
    "관/菅",
    "관/觀",
    "관/貫",
    "관/鑵",
    "관/關",
    "관/雚",
    "관/館",
    "관/鸛"
  ],
  "광": [
    "광/侊",
    "광/光",
    "광/匡",
    "광/広",
    "광/廣",
    "광/曠",
    "광/桄",
    "광/框",
    "광/炚",
    "광/炛",
    "광/爌",
    "광/珖",
    "광/磺",
    "광/筐",
    "광/絖",
    "광/纊",
    "광/茪",
    "광/鑛"
  ],
  "교": [
    "교/交",
    "교/佼",
    "교/喬",
    "교/嘄",
    "교/嘐",
    "교/嚙",
    "교/姣",
    "교/嬌",
    "교/嶠",
    "교/巧",
    "교/撟",
    "교/攪",
    "교/敎",
    "교/教",
    "교/晈",
    "교/暞",
    "교/校",
    "교/榷",
    "교/橋",
    "교/皎",
    "교/矯",
    "교/翹",
    "교/蛟",
    "교/趫",
    "교/蹻",
    "교/較",
    "교/轎",
    "교/郊",
    "교/鄗",
    "교/鉸"
  ],
  "구": [
    "구/丘",
    "구/久",
    "구/九",
    "구/俅",
    "구/俱",
    "구/傴",
    "구/具",
    "구/劬",
    "구/勾",
    "구/區",
    "구/口",
    "구/句",
    "구/叴",
    "구/坵",
    "구/姤",
    "구/媾",
    "구/岣",
    "구/彀",
    "구/戵",
    "구/扣",
    "구/捄",
    "구/搆",
    "구/摳",
    "구/救",
    "구/昫",
    "구/枸",
    "구/構",
    "구/毬",
    "구/求",
    "구/溝",
    "구/漚",
    "구/灸",
    "구/玖",
    "구/玽",
    "구/球",
    "구/璆",
    "구/甌",
    "구/究",
    "구/絿",
    "구/胊",
    "구/臼",
    "구/舊",
    "구/苟",
    "구/蒟",
    "구/衢",
    "구/覯",
    "구/講",
    "구/謳",
    "구/軀",
    "구/逑",
    "구/遘",
    "구/邱",
    "구/釦",
    "구/鉤",
    "구/銶",
    "구/韝",
    "구/韭",
    "구/驅",
    "구/鬮",
    "구/鳩",
    "구/鷗",
    "구/鸜",
    "구/龜"
  ],
  "국": [
    "국/匊",
    "국/国",
    "국/國",
    "국/局",
    "국/掬",
    "국/菊",
    "국/麯",
    "국/麴"
  ],
  "군": [
    "군/君",
    "군/捃",
    "군/群",
    "군/軍",
    "군/郡"
  ],
  "권": [
    "권/券",
    "권/勸",
    "권/卷",
    "권/惓",
    "권/拳",
    "권/捲",
    "권/棬",
    "권/権",
    "권/權",
    "권/淃",
    "권/眷",
    "권/睠",
    "권/綣",
    "권/蜷"
  ],
  "귀": [
    "귀/句",
    "귀/晷",
    "귀/歸",
    "귀/貴",
    "귀/龜"
  ],
  "규": [
    "규/圭",
    "규/奎",
    "규/嬀",
    "규/巋",
    "규/揆",
    "규/暌",
    "규/樛",
    "규/湀",
    "규/潙",
    "규/煃",
    "규/珪",
    "규/窺",
    "규/糾",
    "규/茥",
    "규/葵",
    "규/虯",
    "규/規",
    "규/赳",
    "규/跬",
    "규/逵",
    "규/邽",
    "규/閨",
    "규/闚",
    "규/頍",
    "규/鮭"
  ],
  "균": [
    "균/勻",
    "균/囷",
    "균/均",
    "균/畇",
    "균/筠",
    "균/覠",
    "균/鈞",
    "균/麏",
    "균/龜"
  ],
  "극": [
    "극/亟",
    "극/克",
    "극/剋",
    "극/劇",
    "극/尅",
    "극/極",
    "극/郄",
    "극/隙"
  ],
  "근": [
    "근/劤",
    "근/勤",
    "근/墐",
    "근/嫤",
    "근/巹",
    "근/懃",
    "근/斤",
    "근/根",
    "근/槿",
    "근/漌",
    "근/瑾",
    "근/筋",
    "근/絙",
    "근/菫",
    "근/覲",
    "근/觔",
    "근/謹",
    "근/近"
  ],
  "글": [
    "글/曁"
  ],
  "금": [
    "금/今",
    "금/嶔",
    "금/擒",
    "금/昑",
    "금/檎",
    "금/琴",
    "금/禽",
    "금/芩",
    "금/衾",
    "금/衿",
    "금/金",
    "금/錦",
    "금/黅",
    "금/黚"
  ],
  "기": [
    "기/㠌",
    "기/企",
    "기/伎",
    "기/其",
    "기/冀",
    "기/嗜",
    "기/器",
    "기/圻",
    "기/基",
    "기/埼",
    "기/墍",
    "기/夔",
    "기/奇",
    "기/寄",
    "기/屺",
    "기/岐",
    "기/己",
    "기/幾",
    "기/庋",
    "기/忯",
    "기/愭",
    "기/技",
    "기/掎",
    "기/攲",
    "기/旂",
    "기/旗",
    "기/旣",
    "기/暣",
    "기/曁",
    "기/朞",
    "기/期",
    "기/杞",
    "기/棊",
    "기/棋",
    "기/榿",
    "기/機",
    "기/歧",
    "기/氣",
    "기/汽",
    "기/沂",
    "기/淇",
    "기/炁",
    "기/玘",
    "기/琦",
    "기/琪",
    "기/璂",
    "기/璣",
    "기/畸",
    "기/畿",
    "기/碁",
    "기/磯",
    "기/祁",
    "기/祈",
    "기/祺",
    "기/禨",
    "기/稘",
    "기/箕",
    "기/紀",
    "기/綥",
    "기/綦",
    "기/綺",
    "기/羇",
    "기/羈",
    "기/耭",
    "기/芪",
    "기/芰",
    "기/茤",
    "기/蘄",
    "기/虁",
    "기/覬",
    "기/記",
    "기/豈",
    "기/起",
    "기/錡",
    "기/隑",
    "기/頎",
    "기/飢",
    "기/騎",
    "기/騏",
    "기/驥",
    "기/麒"
  ],
  "긴": [
    "긴/緊"
  ],
  "길": [
    "길/佶",
    "길/吉",
    "길/姞",
    "길/拮",
    "길/桔"
  ],
  "김": [
    "김/金"
  ],
  "나": [
    "나/䏧",
    "나/儸",
    "나/厲",
    "나/喇",
    "나/囉",
    "나/奈",
    "나/娜",
    "나/拏",
    "나/拿",
    "나/挐",
    "나/挪",
    "나/摞",
    "나/曪",
    "나/柰",
    "나/梛",
    "나/瘰",
    "나/砢",
    "나/糯",
    "나/羅",
    "나/蓏",
    "나/覶",
    "나/邏",
    "나/那",
    "나/鑼"
  ],
  "낙": [
    "낙/嗠",
    "낙/樂",
    "낙/洛",
    "낙/犖",
    "낙/珞",
    "낙/絡",
    "낙/諾",
    "낙/酪",
    "낙/駱"
  ],
  "난": [
    "난/丹",
    "난/卵",
    "난/暖",
    "난/欄",
    "난/欒",
    "난/瀾",
    "난/煖",
    "난/爛",
    "난/瓓",
    "난/蘭",
    "난/覶",
    "난/鑾",
    "난/餪",
    "난/鸞"
  ],
  "남": [
    "남/㛦",
    "남/南",
    "남/喃",
    "남/嵐",
    "남/擥",
    "남/攬",
    "남/枏",
    "남/楠",
    "남/欖",
    "남/湳",
    "남/濫",
    "남/灆",
    "남/爁",
    "남/璼",
    "남/男",
    "남/纜",
    "남/藍",
    "남/覽"
  ],
  "낭": [
    "낭/㢃",
    "낭/囊",
    "낭/娘",
    "낭/廊",
    "낭/曩",
    "낭/朗",
    "낭/榔",
    "낭/浪",
    "낭/瀼",
    "낭/烺",
    "낭/琅",
    "낭/瑯",
    "낭/硠",
    "낭/稂",
    "낭/良",
    "낭/莨",
    "낭/郎",
    "낭/郞",
    "낭/閬",
    "낭/駺"
  ],
  "내": [
    "내/騋"
  ],
  "녀": [
    "녀/女"
  ],
  "년": [
    "년/年",
    "년/碾",
    "년/秊"
  ],
  "념": [
    "념/拈"
  ],
  "녕": [
    "녕/嚀",
    "녕/寗",
    "녕/寧"
  ],
  "노": [
    "노/䛝",
    "노/努",
    "노/勞",
    "노/嚧",
    "노/壚",
    "노/孥",
    "노/峱",
    "노/弩",
    "노/撈",
    "노/櫓",
    "노/櫨",
    "노/滷",
    "노/潞",
    "노/澇",
    "노/瀘",
    "노/爐",
    "노/瑙",
    "노/璐",
    "노/瓐",
    "노/盧",
    "노/艪",
    "노/艫",
    "노/芦",
    "노/蕗",
    "노/蘆",
    "노/虜",
    "노/路",
    "노/輅",
    "노/酪",
    "노/鐪",
    "노/鑪",
    "노/露",
    "노/魯",
    "노/鱸",
    "노/鷺",
    "노/鹵"
  ],
  "녹": [
    "녹/彔",
    "녹/淥",
    "녹/漉",
    "녹/碌",
    "녹/祿",
    "녹/簏",
    "녹/綠",
    "녹/菉",
    "녹/錄",
    "녹/騄",
    "녹/鹿",
    "녹/麓"
  ],
  "뇌": [
    "뇌/餧"
  ],
  "뇨": [
    "뇨/鐃"
  ],
  "눈": [
    "눈/枘"
  ],
  "늠": [
    "늠/凛",
    "늠/凜",
    "늠/廩",
    "늠/澟",
    "늠/菻"
  ],
  "능": [
    "능/楞",
    "능/稜",
    "능/綾",
    "능/能",
    "능/菱",
    "능/蔆",
    "능/陵"
  ],
  "다": [
    "다/多",
    "다/夛",
    "다/茤",
    "다/茶"
  ],
  "단": [
    "단/㫜",
    "단/丹",
    "단/亶",
    "단/但",
    "단/單",
    "단/團",
    "단/壇",
    "단/彖",
    "단/担",
    "단/旦",
    "단/椴",
    "단/檀",
    "단/段",
    "단/湍",
    "단/漙",
    "단/煓",
    "단/端",
    "단/簞",
    "단/緞",
    "단/耑",
    "단/袒",
    "단/鄲",
    "단/鍛"
  ],
  "달": [
    "달/妲",
    "달/澾",
    "달/獺",
    "달/達",
    "달/闥",
    "달/韃"
  ],
  "담": [
    "담/鐔"
  ],
  "당": [
    "당/贛"
  ],
  "대": [
    "대/㬃",
    "대/㬣",
    "대/代",
    "대/坮",
    "대/垈",
    "대/大",
    "대/對",
    "대/岱",
    "대/待",
    "대/戴",
    "대/抬",
    "대/擡",
    "대/旲",
    "대/汏",
    "대/臺",
    "대/隊"
  ],
  "댁": [
    "댁/宅"
  ],
  "덕": [
    "덕/徳",
    "덕/德",
    "덕/悳"
  ],
  "도": [
    "도/到",
    "도/圖",
    "도/塗",
    "도/壔",
    "도/夲",
    "도/導",
    "도/島",
    "도/嶋",
    "도/度",
    "도/弢",
    "도/徒",
    "도/慆",
    "도/挑",
    "도/掉",
    "도/掏",
    "도/搗",
    "도/搯",
    "도/擣",
    "도/桃",
    "도/棹",
    "도/檮",
    "도/櫂",
    "도/洮",
    "도/涂",
    "도/淘",
    "도/渡",
    "도/滔",
    "도/濤",
    "도/燾",
    "도/睹",
    "도/祹",
    "도/禱",
    "도/稌",
    "도/稻",
    "도/菟",
    "도/萄",
    "도/覩",
    "도/跳",
    "도/途",
    "도/道",
    "도/都",
    "도/鍍",
    "도/闍",
    "도/陶",
    "도/鞀",
    "도/馟",
    "도/鼗"
  ],
  "돈": [
    "돈/墩",
    "돈/弴",
    "돈/惇",
    "돈/敦",
    "돈/旽",
    "돈/暾",
    "돈/潡",
    "돈/燉",
    "돈/躉"
  ],
  "돌": [
    "돌/乭",
    "돌/突"
  ],
  "동": [
    "동/仝",
    "동/侗",
    "동/僮",
    "동/冬",
    "동/動",
    "동/勭",
    "동/同",
    "동/哃",
    "동/垌",
    "동/峒",
    "동/彤",
    "동/憧",
    "동/曈",
    "동/朣",
    "동/東",
    "동/桐",
    "동/棟",
    "동/橦",
    "동/洞",
    "동/涷",
    "동/潼",
    "동/烔",
    "동/瞳",
    "동/童",
    "동/艟",
    "동/茼",
    "동/董",
    "동/蕫",
    "동/蝀",
    "동/銅"
  ],
  "두": [
    "두/杜",
    "두/枓",
    "두/荳",
    "두/讀",
    "두/豆",
    "두/逗",
    "두/阧",
    "두/頭"
  ],
  "득": [
    "득/得"
  ],
  "라": [
    "라/儸",
    "라/厲",
    "라/喇",
    "라/摞",
    "라/砢",
    "라/蓏",
    "라/覶",
    "라/邏",
    "라/鑼"
  ],
  "락": [
    "락/嗠",
    "락/樂",
    "락/洛",
    "락/犖",
    "락/珞",
    "락/絡",
    "락/酪"
  ],
  "란": [
    "란/丹",
    "란/卵",
    "란/幱",
    "란/欒",
    "란/瀾",
    "란/爛",
    "란/瓓",
    "란/蘭",
    "란/覶",
    "란/鑾",
    "란/鸞"
  ],
  "람": [
    "람/嵐"
  ],
  "랑": [
    "랑/㢃",
    "랑/廊",
    "랑/朗",
    "랑/榔",
    "랑/浪",
    "랑/烺",
    "랑/琅",
    "랑/瑯",
    "랑/莨",
    "랑/郎",
    "랑/郞",
    "랑/閬"
  ],
  "래": [
    "래/來",
    "래/崍",
    "래/徠",
    "래/来",
    "래/淶",
    "래/萊",
    "래/騋"
  ],
  "량": [
    "량/粮",
    "량/粱"
  ],
  "려": [
    "려/勵",
    "려/厲",
    "려/呂",
    "려/唳",
    "려/慮",
    "려/梠",
    "려/櫚",
    "려/濾",
    "려/礪",
    "려/糲",
    "려/藜",
    "려/邌",
    "려/鑢",
    "려/閭",
    "려/麗"
  ],
  "력": [
    "력/力",
    "력/曆",
    "력/歷",
    "력/礫",
    "력/轣",
    "력/酈"
  ],
  "련": [
    "련/孌",
    "련/戀",
    "련/湅",
    "련/漣",
    "련/煉",
    "련/璉",
    "련/練",
    "련/聯",
    "련/蓮",
    "련/連",
    "련/鍊",
    "련/鰊",
    "련/鰱"
  ],
  "렬": [
    "렬/冽",
    "렬/列",
    "렬/洌"
  ],
  "렴": [
    "렴/廉",
    "렴/斂",
    "렴/槏",
    "렴/濂",
    "렴/瀲",
    "렴/簾"
  ],
  "령": [
    "령/令",
    "령/伶",
    "령/呤",
    "령/姈",
    "령/岭",
    "령/岺",
    "령/嶺",
    "령/怜",
    "령/昤",
    "령/泠",
    "령/澪",
    "령/玲",
    "령/秢",
    "령/羚",
    "령/聆",
    "령/逞",
    "령/鈴",
    "령/零",
    "령/領",
    "령/齡"
  ],
  "례": [
    "례/例",
    "례/列",
    "례/澧",
    "례/礼",
    "례/禮",
    "례/醴"
  ],
  "로": [
    "로/櫨",
    "로/芦",
    "로/酪",
    "로/鱸"
  ],
  "록": [
    "록/彔",
    "록/淥",
    "록/漉",
    "록/碌",
    "록/祿",
    "록/簏",
    "록/綠",
    "록/菉",
    "록/錄",
    "록/鹿"
  ],
  "뢰": [
    "뢰/纍"
  ],
  "료": [
    "료/寮",
    "료/聊",
    "료/蓼"
  ],
  "룡": [
    "룡/竜",
    "룡/龍",
    "룡/龒"
  ],
  "루": [
    "루/纍"
  ],
  "류": [
    "류/柳",
    "류/榴",
    "류/橊",
    "류/瀏",
    "류/琉",
    "류/瑠",
    "류/留",
    "류/纍",
    "류/遛",
    "류/類",
    "류/鶹"
  ],
  "륙": [
    "륙/賁"
  ],
  "륜": [
    "륜/侖",
    "륜/倫",
    "륜/圇",
    "륜/崘",
    "륜/崙",
    "륜/掄",
    "륜/輪",
    "륜/錀"
  ],
  "률": [
    "률/嵂",
    "률/律",
    "률/栗",
    "률/溧",
    "률/率",
    "률/瑮"
  ],
  "름": [
    "름/凛",
    "름/凜"
  ],
  "릉": [
    "릉/菱",
    "릉/蔆"
  ],
  "리": [
    "리/俐",
    "리/利",
    "리/厘",
    "리/吏",
    "리/哩",
    "리/唎",
    "리/悧",
    "리/摛",
    "리/李",
    "리/梨",
    "리/浬",
    "리/涖",
    "리/漓",
    "리/犁",
    "리/犂",
    "리/理",
    "리/璃",
    "리/离",
    "리/籬",
    "리/莅",
    "리/莉",
    "리/螭",
    "리/裏",
    "리/裡",
    "리/邐",
    "리/里",
    "리/釐",
    "리/鯉",
    "리/麗"
  ],
  "린": [
    "린/䗲",
    "린/吝",
    "린/嶙",
    "린/悋",
    "린/撛",
    "린/橉",
    "린/潾",
    "린/璘",
    "린/磷",
    "린/粼",
    "린/繗",
    "린/藺",
    "린/鄰",
    "린/鏻",
    "린/隣",
    "린/麟"
  ],
  "림": [
    "림/晽",
    "림/林",
    "림/棽",
    "림/玪",
    "림/琳",
    "림/碄",
    "림/臨"
  ],
  "립": [
    "립/岦",
    "립/立",
    "립/笠"
  ],
  "마": [
    "마/媽",
    "마/瑪",
    "마/碼",
    "마/磨"
  ],
  "만": [
    "만/万",
    "만/卍",
    "만/墁",
    "만/娩",
    "만/巒",
    "만/幔",
    "만/彎",
    "만/挽",
    "만/曼",
    "만/滿",
    "만/灣",
    "만/萬",
    "만/蹣",
    "만/輓",
    "만/鏋",
    "만/鏝",
    "만/鬘"
  ],
  "말": [
    "말/秣",
    "말/茉"
  ],
  "망": [
    "망/方"
  ],
  "매": [
    "매/妹",
    "매/媒",
    "매/枚",
    "매/梅",
    "매/楳",
    "매/每",
    "매/沬",
    "매/玫",
    "매/苺",
    "매/莓",
    "매/買",
    "매/賣",
    "매/邁",
    "매/霉"
  ],
  "맹": [
    "맹/孟",
    "맹/氓",
    "맹/猛",
    "맹/甍",
    "맹/甿",
    "맹/盟",
    "맹/萌"
  ],
  "멱": [
    "멱/蓂"
  ],
  "명": [
    "명/䳟",
    "명/名",
    "명/命",
    "명/慏",
    "명/明",
    "명/椧",
    "명/洺",
    "명/溟",
    "명/皿",
    "명/眀",
    "명/瞑",
    "명/茗",
    "명/萌",
    "명/蓂",
    "명/銘",
    "명/鳴"
  ],
  "모": [
    "모/侔",
    "모/冒",
    "모/募",
    "모/慔",
    "모/慕",
    "모/摸",
    "모/旄",
    "모/某",
    "모/模",
    "모/橅",
    "모/母",
    "모/瑁",
    "모/眸",
    "모/芼",
    "모/茅",
    "모/貌",
    "모/軞",
    "모/髦"
  ],
  "목": [
    "목/木",
    "목/牧",
    "목/睦",
    "목/穆",
    "목/苜"
  ],
  "몽": [
    "몽/夢",
    "몽/萌"
  ],
  "묘": [
    "묘/妙",
    "묘/廟",
    "묘/描",
    "묘/昴",
    "묘/杳",
    "묘/淼",
    "묘/畝",
    "묘/竗",
    "묘/苗",
    "묘/錨"
  ],
  "무": [
    "무/儛",
    "무/務",
    "무/廡",
    "무/憮",
    "무/懋",
    "무/戊",
    "무/拇",
    "무/撫",
    "무/无",
    "무/楙",
    "무/橅",
    "무/武",
    "무/珷",
    "무/畝",
    "무/繆",
    "무/舞",
    "무/茂",
    "무/貿",
    "무/霧",
    "무/騖",
    "무/髦"
  ],
  "묵": [
    "묵/嘿",
    "묵/墨",
    "묵/默"
  ],
  "문": [
    "문/問",
    "문/悗",
    "문/抆",
    "문/捫",
    "문/文",
    "문/汶",
    "문/炆",
    "문/璊",
    "문/紋",
    "문/聞",
    "문/脗",
    "문/門",
    "문/雯"
  ],
  "미": [
    "미/亹",
    "미/侎",
    "미/冞",
    "미/味",
    "미/娓",
    "미/媄",
    "미/媺",
    "미/嵄",
    "미/嵋",
    "미/弥",
    "미/彌",
    "미/敉",
    "미/楣",
    "미/洣",
    "미/渼",
    "미/濔",
    "미/瀰",
    "미/煝",
    "미/瑂",
    "미/米",
    "미/美",
    "미/苿",
    "미/薇",
    "미/蘪",
    "미/蘼",
    "미/躾"
  ],
  "민": [
    "민/䃉",
    "민/䪸",
    "민/岷",
    "민/忞",
    "민/忟",
    "민/慜",
    "민/敃",
    "민/敏",
    "민/旻",
    "민/旼",
    "민/暋",
    "민/民",
    "민/潣",
    "민/玟",
    "민/珉",
    "민/琘",
    "민/琝",
    "민/瑉",
    "민/盿",
    "민/砇",
    "민/脗",
    "민/鈱",
    "민/閔",
    "민/閩",
    "민/黽"
  ],
  "박": [
    "박/亳",
    "박/博",
    "박/墣",
    "박/朴",
    "박/樸",
    "박/欂",
    "박/泊",
    "박/牔",
    "박/珀",
    "박/璞",
    "박/縛",
    "박/舶",
    "박/薄",
    "박/鉑",
    "박/鎛",
    "박/駮"
  ],
  "반": [
    "반/伴",
    "반/弁",
    "반/扳",
    "반/搫",
    "반/搬",
    "반/朌",
    "반/泮",
    "반/潘",
    "반/班",
    "반/畔",
    "반/盤",
    "반/盼",
    "반/磐",
    "반/磻",
    "반/礬",
    "반/肦",
    "반/般",
    "반/蟠",
    "반/返",
    "반/頖",
    "반/飯"
  ],
  "발": [
    "발/炦"
  ],
  "방": [
    "방/仿",
    "방/倣",
    "방/厖",
    "방/坊",
    "방/夆",
    "방/幇",
    "방/幫",
    "방/房",
    "방/搒",
    "방/放",
    "방/方",
    "방/旁",
    "방/昉",
    "방/枋",
    "방/榜",
    "방/牓",
    "방/肪",
    "방/舫",
    "방/舽",
    "방/芳",
    "방/訪",
    "방/邦",
    "방/髣"
  ],
  "배": [
    "배/䔒",
    "배/俳",
    "배/倍",
    "배/坏",
    "배/培",
    "배/拜",
    "배/杯",
    "배/湃",
    "배/焙",
    "배/琲",
    "배/盃",
    "배/背",
    "배/蓓",
    "배/裴",
    "배/裵",
    "배/賠",
    "배/輩",
    "배/配",
    "배/陪"
  ],
  "백": [
    "백/䞟",
    "백/伯",
    "백/佰",
    "백/帛",
    "백/柏",
    "백/栢",
    "백/珀",
    "백/白",
    "백/百",
    "백/苩",
    "백/魄"
  ],
  "번": [
    "번/賁"
  ],
  "범": [
    "범/凡",
    "범/帆",
    "범/梵",
    "범/氾",
    "범/汎",
    "범/渢",
    "범/犯",
    "범/笵",
    "범/範",
    "범/范",
    "범/訉",
    "범/釩",
    "범/颿"
  ],
  "법": [
    "법/法",
    "법/琺"
  ],
  "벽": [
    "벽/壁",
    "벽/檗",
    "벽/璧",
    "벽/疈",
    "벽/碧",
    "벽/蘗",
    "벽/辟",
    "벽/闢",
    "벽/鼊"
  ],
  "변": [
    "변/卞",
    "변/弁",
    "변/忭",
    "변/抃",
    "변/籩",
    "변/變",
    "변/賆",
    "변/辨",
    "변/辯",
    "변/邊",
    "변/釆",
    "변/駢",
    "변/騈",
    "변/鴘"
  ],
  "병": [
    "병/丙",
    "병/並",
    "병/倂",
    "병/屛",
    "병/并",
    "병/幷",
    "병/抦",
    "병/昞",
    "병/昺",
    "병/枋",
    "병/柄",
    "병/棅",
    "병/炳",
    "병/秉",
    "병/竝",
    "병/輧",
    "병/鈵",
    "병/餠",
    "병/駢",
    "병/騈"
  ],
  "보": [
    "보/㻄",
    "보/䀯",
    "보/俌",
    "보/保",
    "보/報",
    "보/宝",
    "보/寶",
    "보/普",
    "보/步",
    "보/歩",
    "보/洑",
    "보/湺",
    "보/潽",
    "보/珤",
    "보/甫",
    "보/補",
    "보/譜",
    "보/輔",
    "보/靌",
    "보/鴇",
    "보/黼"
  ],
  "복": [
    "복/匐",
    "복/卜",
    "복/墣",
    "복/宓",
    "복/幞",
    "복/復",
    "복/服",
    "복/濮",
    "복/福",
    "복/箙",
    "복/腹",
    "복/茯",
    "복/蔔",
    "복/複",
    "복/覆",
    "복/輹",
    "복/鍑",
    "복/馥",
    "복/鰒",
    "복/鵩"
  ],
  "본": [
    "본/本"
  ],
  "봉": [
    "봉/丰",
    "봉/俸",
    "봉/夆",
    "봉/奉",
    "봉/封",
    "봉/峯",
    "봉/峰",
    "봉/捧",
    "봉/梵",
    "봉/浲",
    "봉/漨",
    "봉/烽",
    "봉/熢",
    "봉/縫",
    "봉/芃",
    "봉/蜂",
    "봉/逢",
    "봉/鳳",
    "봉/鴌"
  ],
  "부": [
    "부/付",
    "부/俘",
    "부/俯",
    "부/傅",
    "부/副",
    "부/咐",
    "부/埠",
    "부/夫",
    "부/孚",
    "부/富",
    "부/府",
    "부/復",
    "부/扶",
    "부/抔",
    "부/拊",
    "부/掊",
    "부/敷",
    "부/浮",
    "부/溥",
    "부/玞",
    "부/符",
    "부/筟",
    "부/簿",
    "부/缶",
    "부/胕",
    "부/艀",
    "부/芙",
    "부/莩",
    "부/袝",
    "부/裒",
    "부/賦",
    "부/赴",
    "부/部",
    "부/釜",
    "부/阜",
    "부/附",
    "부/頫",
    "부/駙"
  ],
  "분": [
    "분/体",
    "분/分",
    "분/吩",
    "분/噴",
    "분/奔",
    "분/奮",
    "분/扮",
    "분/昐",
    "분/朌",
    "분/枌",
    "분/棻",
    "분/棼",
    "분/氛",
    "분/汾",
    "분/湓",
    "분/濆",
    "분/畚",
    "분/盆",
    "분/砏",
    "분/肦",
    "분/芬",
    "분/賁",
    "분/錀",
    "분/黺"
  ],
  "비": [
    "비/賁"
  ],
  "빈": [
    "빈/份",
    "빈/儐",
    "빈/彬",
    "빈/擯",
    "빈/斌",
    "빈/檳",
    "빈/汃",
    "빈/浜",
    "빈/濱",
    "빈/瀕",
    "빈/玭",
    "빈/璸",
    "빈/穦",
    "빈/豳",
    "빈/賓",
    "빈/贇",
    "빈/邠",
    "빈/鑌",
    "빈/霦",
    "빈/馪"
  ],
  "사": [
    "사/乍",
    "사/事",
    "사/仕",
    "사/似",
    "사/使",
    "사/俟",
    "사/傞",
    "사/史",
    "사/司",
    "사/唆",
    "사/嗣",
    "사/士",
    "사/娑",
    "사/師",
    "사/徙",
    "사/思",
    "사/斜",
    "사/斯",
    "사/査",
    "사/榭",
    "사/汜",
    "사/泗",
    "사/澌",
    "사/獅",
    "사/社",
    "사/私",
    "사/竢",
    "사/糸",
    "사/紗",
    "사/肆",
    "사/舍",
    "사/裟",
    "사/詞",
    "사/謝",
    "사/賜",
    "사/赦",
    "사/辭",
    "사/霍",
    "사/飼",
    "사/駛",
    "사/駟",
    "사/魦",
    "사/鰤"
  ],
  "삭": [
    "삭/數"
  ],
  "산": [
    "산/㦃",
    "산/傘",
    "산/孿",
    "산/山",
    "산/散",
    "산/橵",
    "산/汕",
    "산/狻",
    "산/祘",
    "산/算",
    "산/繖",
    "산/選"
  ],
  "삼": [
    "삼/三",
    "삼/參",
    "삼/摻",
    "삼/杉",
    "삼/森",
    "삼/滲",
    "삼/蔘",
    "삼/衫",
    "삼/鈒",
    "삼/髟"
  ],
  "상": [
    "상/上",
    "상/像",
    "상/償",
    "상/商",
    "상/嘗",
    "상/塽",
    "상/嫦",
    "상/尙",
    "상/常",
    "상/床",
    "상/庠",
    "상/想",
    "상/慡",
    "상/樣",
    "상/橡",
    "상/湘",
    "상/潒",
    "상/爽",
    "상/牀",
    "상/狀",
    "상/甞",
    "상/相",
    "상/祥",
    "상/翔",
    "상/裳",
    "상/詳",
    "상/象",
    "상/賞"
  ],
  "색": [
    "색/漬"
  ],
  "생": [
    "생/牲",
    "생/生",
    "생/省",
    "생/笙"
  ],
  "서": [
    "서/㠘",
    "서/㥠",
    "서/㷂",
    "서/偦",
    "서/叙",
    "서/嶼",
    "서/庶",
    "서/徐",
    "서/恕",
    "서/捿",
    "서/揟",
    "서/撕",
    "서/敍",
    "서/敘",
    "서/曙",
    "서/書",
    "서/棲",
    "서/澨",
    "서/瑞",
    "서/稰",
    "서/筮",
    "서/紓",
    "서/絮",
    "서/緖",
    "서/縃",
    "서/署",
    "서/胥",
    "서/舒",
    "서/藇",
    "서/誓",
    "서/諝",
    "서/遾",
    "서/黍"
  ],
  "석": [
    "석/䄷",
    "석/夕",
    "석/奭",
    "석/席",
    "석/惜",
    "석/晰",
    "석/晳",
    "석/汐",
    "석/澤",
    "석/石",
    "석/碩",
    "석/繹",
    "석/蓆",
    "석/褯",
    "석/釋",
    "석/錫"
  ],
  "선": [
    "선/㻽",
    "선/䁢",
    "선/亘",
    "선/仙",
    "선/先",
    "선/善",
    "선/墡",
    "선/姺",
    "선/嫙",
    "선/嬋",
    "선/宣",
    "선/尟",
    "선/屳",
    "선/愃",
    "선/扇",
    "선/擐",
    "선/旋",
    "선/歚",
    "선/洒",
    "선/洗",
    "선/渲",
    "선/煽",
    "선/珗",
    "선/琁",
    "선/瑄",
    "선/璇",
    "선/璿",
    "선/盤",
    "선/省",
    "선/禪",
    "선/筅",
    "선/線",
    "선/羨",
    "선/腺",
    "선/船",
    "선/詵",
    "선/譔",
    "선/譱",
    "선/選",
    "선/銑",
    "선/鐥",
    "선/鮮"
  ],
  "설": [
    "설/偰",
    "설/卨",
    "설/契",
    "설/揲",
    "설/楔",
    "설/禼",
    "설/蔎",
    "설/薛",
    "설/設",
    "설/說",
    "설/雪",
    "설/齧"
  ],
  "섬": [
    "섬/剡",
    "섬/摻",
    "섬/暹",
    "섬/纖",
    "섬/諶",
    "섬/贍",
    "섬/銛",
    "섬/閃",
    "섬/陝"
  ],
  "섭": [
    "섭/拾",
    "섭/攝",
    "섭/涉",
    "섭/灄",
    "섭/燮",
    "섭/葉",
    "섭/躞",
    "섭/鑷"
  ],
  "성": [
    "성/城",
    "성/姓",
    "성/娍",
    "성/宬",
    "성/性",
    "성/惺",
    "성/成",
    "성/星",
    "성/晟",
    "성/晠",
    "성/珹",
    "성/瑆",
    "성/盛",
    "성/省",
    "성/聖",
    "성/聲",
    "성/胜",
    "성/誠",
    "성/貹",
    "성/騂"
  ],
  "세": [
    "세/世",
    "세/勢",
    "세/彗",
    "세/忕",
    "세/歲",
    "세/洒",
    "세/洗",
    "세/稅",
    "세/細",
    "세/說",
    "세/貰",
    "세/銴"
  ],
  "소": [
    "소/䘘",
    "소/䨭",
    "소/佋",
    "소/傃",
    "소/劭",
    "소/卲",
    "소/召",
    "소/咲",
    "소/嘯",
    "소/埽",
    "소/塐",
    "소/塑",
    "소/少",
    "소/巢",
    "소/愫",
    "소/所",
    "소/掃",
    "소/昭",
    "소/沼",
    "소/泝",
    "소/溯",
    "소/瀟",
    "소/炤",
    "소/燒",
    "소/玿",
    "소/璅",
    "소/甦",
    "소/疎",
    "소/疏",
    "소/稍",
    "소/穌",
    "소/笑",
    "소/箾",
    "소/素",
    "소/紹",
    "소/繅",
    "소/肖",
    "소/艘",
    "소/蘇",
    "소/訴",
    "소/詔",
    "소/逍",
    "소/邵",
    "소/酥",
    "소/銷",
    "소/霄",
    "소/韶"
  ],
  "속": [
    "속/數"
  ],
  "손": [
    "손/孫",
    "손/巽",
    "손/蓀",
    "손/遜",
    "손/選"
  ],
  "솔": [
    "솔/䢦",
    "솔/帥",
    "솔/率"
  ],
  "송": [
    "송/宋",
    "송/憽",
    "송/松",
    "송/淞",
    "송/竦",
    "송/誦",
    "송/送",
    "송/頌",
    "송/鬆"
  ],
  "솰": [
    "솰/選"
  ],
  "수": [
    "수/㻽",
    "수/修",
    "수/受",
    "수/垂",
    "수/壽",
    "수/守",
    "수/宿",
    "수/寿",
    "수/峀",
    "수/帥",
    "수/戍",
    "수/授",
    "수/搜",
    "수/收",
    "수/數",
    "수/樹",
    "수/殊",
    "수/水",
    "수/洙",
    "수/溲",
    "수/濉",
    "수/琇",
    "수/璲",
    "수/瓍",
    "수/睟",
    "수/睢",
    "수/秀",
    "수/穂",
    "수/穗",
    "수/竪",
    "수/籔",
    "수/粹",
    "수/綏",
    "수/繡",
    "수/脺",
    "수/膸",
    "수/蒐",
    "수/蓚",
    "수/豎",
    "수/賥",
    "수/輸",
    "수/遂",
    "수/邃",
    "수/酬",
    "수/銖",
    "수/陲",
    "수/隋",
    "수/隧",
    "수/隨",
    "수/需",
    "수/須",
    "수/颼",
    "수/饈",
    "수/首"
  ],
  "숙": [
    "숙/俶",
    "숙/倏",
    "숙/儵",
    "숙/叔",
    "숙/塾",
    "숙/夙",
    "숙/婌",
    "숙/宿",
    "숙/橚",
    "숙/淑",
    "숙/潚",
    "숙/熟",
    "숙/琡",
    "숙/璹",
    "숙/肅",
    "숙/菽",
    "숙/驌",
    "숙/鷫"
  ],
  "순": [
    "순/侚",
    "순/峋",
    "순/巡",
    "순/徇",
    "순/循",
    "순/恂",
    "순/旬",
    "순/橓",
    "순/洵",
    "순/淳",
    "순/焞",
    "순/珣",
    "순/畃",
    "순/盾",
    "순/眴",
    "순/瞬",
    "순/筍",
    "순/純",
    "순/脣",
    "순/舜",
    "순/荀",
    "순/蓴",
    "순/蕣",
    "순/詢",
    "순/諄",
    "순/醇",
    "순/錞",
    "순/順",
    "순/馴",
    "순/駨"
  ],
  "술": [
    "술/戌",
    "술/絉",
    "술/術",
    "술/述"
  ],
  "숭": [
    "숭/崇",
    "숭/崧",
    "숭/嵩"
  ],
  "슬": [
    "슬/㻭",
    "슬/瑟",
    "슬/璱"
  ],
  "습": [
    "습/拾",
    "습/習"
  ],
  "승": [
    "승/㞼",
    "승/丞",
    "승/乘",
    "승/僧",
    "승/勝",
    "승/升",
    "승/承",
    "승/昇",
    "승/榺",
    "승/氶",
    "승/胜",
    "승/阩",
    "승/陞",
    "승/陹"
  ],
  "시": [
    "시/侍",
    "시/偲",
    "시/啻",
    "시/塒",
    "시/始",
    "시/媞",
    "시/媤",
    "시/市",
    "시/恃",
    "시/施",
    "시/是",
    "시/昰",
    "시/時",
    "시/枲",
    "시/柴",
    "시/毸",
    "시/沶",
    "시/漦",
    "시/澌",
    "시/眂",
    "시/示",
    "시/禔",
    "시/絁",
    "시/翅",
    "시/蒔",
    "시/蓍",
    "시/視",
    "시/試",
    "시/詩",
    "시/諟",
    "시/諡",
    "시/鍉"
  ],
  "식": [
    "식/寔",
    "식/式",
    "식/息",
    "식/拭",
    "식/栻",
    "식/植",
    "식/殖",
    "식/湜",
    "식/識",
    "식/食",
    "식/飾"
  ],
  "신": [
    "신/伸",
    "신/信",
    "신/呻",
    "신/哂",
    "신/姺",
    "신/宸",
    "신/愼",
    "신/新",
    "신/晨",
    "신/璶",
    "신/申",
    "신/紳",
    "신/臣",
    "신/薪",
    "신/蜃",
    "신/訊",
    "신/贐",
    "신/身",
    "신/辛",
    "신/辰",
    "신/迅",
    "신/頣",
    "신/駪"
  ],
  "실": [
    "실/実",
    "실/室",
    "실/實",
    "실/悉"
  ],
  "심": [
    "심/審",
    "심/尋",
    "심/心",
    "심/沁",
    "심/沈",
    "심/深",
    "심/燖",
    "심/甚",
    "심/芯",
    "심/諶",
    "심/鐔"
  ],
  "십": [
    "십/拾"
  ],
  "아": [
    "아/亜",
    "아/亞",
    "아/児",
    "아/兒",
    "아/哦",
    "아/啊",
    "아/妸",
    "아/妿",
    "아/娥",
    "아/娿",
    "아/婀",
    "아/峨",
    "아/峩",
    "아/我",
    "아/猗",
    "아/皒",
    "아/砑",
    "아/硪",
    "아/笌",
    "아/芽",
    "아/衙",
    "아/迓",
    "아/錏",
    "아/阿",
    "아/雅"
  ],
  "악": [
    "악/偓",
    "악/咢",
    "악/噩",
    "악/岳",
    "악/嶽",
    "악/幄",
    "악/握",
    "악/樂",
    "악/渥",
    "악/萼",
    "악/覨",
    "악/諤",
    "악/鄂",
    "악/鶚",
    "악/齷"
  ],
  "안": [
    "안/䭓",
    "안/侒",
    "안/姲",
    "안/婩",
    "안/安",
    "안/岸",
    "안/晏",
    "안/案",
    "안/桉",
    "안/眼",
    "안/矸",
    "안/雁",
    "안/顔",
    "안/鴈"
  ],
  "알": [
    "알/鳦"
  ],
  "암": [
    "암/唵",
    "암/岩",
    "암/嵓",
    "암/巖",
    "암/庵",
    "암/菴",
    "암/葊",
    "암/蓭",
    "암/諳",
    "암/頷",
    "암/馣"
  ],
  "애": [
    "애/㶼",
    "애/䝽",
    "애/厓",
    "애/崕",
    "애/崖",
    "애/愛",
    "애/曖",
    "애/艾",
    "애/薆",
    "애/藹",
    "애/靄"
  ],
  "앵": [
    "앵/鶯"
  ],
  "야": [
    "야/倻",
    "야/埜",
    "야/惹",
    "야/若",
    "야/野"
  ],
  "약": [
    "약/惹",
    "약/籲",
    "약/若"
  ],
  "양": [
    "양/亮",
    "양/俍",
    "양/倆",
    "양/兩",
    "양/凉",
    "양/喨",
    "양/揚",
    "양/攘",
    "양/敭",
    "양/昜",
    "양/暘",
    "양/梁",
    "양/楊",
    "양/樑",
    "양/樣",
    "양/洋",
    "양/涼",
    "양/漾",
    "양/瀁",
    "양/瀼",
    "양/煬",
    "양/眻",
    "양/粮",
    "양/粱",
    "양/糧",
    "양/羊",
    "양/良",
    "양/蘘",
    "양/襄",
    "양/諒",
    "양/讓",
    "양/踉",
    "양/量",
    "양/陽",
    "양/颺",
    "양/養",
    "양/驤"
  ],
  "어": [
    "어/䘘",
    "어/唹",
    "어/御",
    "어/於",
    "어/語",
    "어/飫"
  ],
  "억": [
    "억/億",
    "억/憶"
  ],
  "언": [
    "언/傿",
    "언/嫣",
    "언/彥",
    "언/彦",
    "언/言",
    "언/諺",
    "언/讞",
    "언/鄢"
  ],
  "얼": [
    "얼/瓛"
  ],
  "엄": [
    "엄/俺",
    "엄/儼",
    "엄/厳",
    "엄/嚴",
    "엄/崦",
    "엄/广",
    "엄/曮",
    "엄/龑"
  ],
  "업": [
    "업/業",
    "업/鄴"
  ],
  "여": [
    "여/予",
    "여/勵",
    "여/呂",
    "여/唳",
    "여/女",
    "여/如",
    "여/悆",
    "여/慮",
    "여/旅",
    "여/櫚",
    "여/濾",
    "여/璵",
    "여/糲",
    "여/舁",
    "여/與",
    "여/艅",
    "여/藜",
    "여/閭",
    "여/麗"
  ],
  "역": [
    "역/力",
    "역/域",
    "역/嶧",
    "역/役",
    "역/懌",
    "역/易",
    "역/晹",
    "역/曆",
    "역/淢",
    "역/澤",
    "역/繹",
    "역/譯",
    "역/轣",
    "역/酈",
    "역/釋",
    "역/驛"
  ],
  "연": [
    "연/㜣",
    "연/䂩",
    "연/兖",
    "연/兗",
    "연/嚥",
    "연/囦",
    "연/均",
    "연/埏",
    "연/堧",
    "연/妍",
    "연/姢",
    "연/姸",
    "연/娟",
    "연/娫",
    "연/嬿",
    "연/孌",
    "연/宴",
    "연/年",
    "연/延",
    "연/戀",
    "연/戭",
    "연/挻",
    "연/掾",
    "연/曣",
    "연/椽",
    "연/沇",
    "연/沿",
    "연/涓",
    "연/淵",
    "연/渊",
    "연/渷",
    "연/演",
    "연/漣",
    "연/然",
    "연/煉",
    "연/煙",
    "연/燕",
    "연/瑌",
    "연/璉",
    "연/瓀",
    "연/硏",
    "연/硯",
    "연/碾",
    "연/秊",
    "연/筵",
    "연/緣",
    "연/練",
    "연/縯",
    "연/聯",
    "연/莚",
    "연/蓮",
    "연/衍",
    "연/讌",
    "연/軟",
    "연/輭",
    "연/連",
    "연/醼",
    "연/鍊",
    "연/鳶"
  ],
  "열": [
    "열/冽",
    "열/列",
    "열/悅",
    "열/洌",
    "열/潱",
    "열/說",
    "열/閱"
  ],
  "염": [
    "염/冉",
    "염/廉",
    "염/念",
    "염/恬",
    "염/懕",
    "염/扊",
    "염/拈",
    "염/斂",
    "염/染",
    "염/濂",
    "염/瀲",
    "염/灩",
    "염/炎",
    "염/焰",
    "염/琰",
    "염/簾",
    "염/艶",
    "염/艷",
    "염/苒",
    "염/閻",
    "염/饜"
  ],
  "엽": [
    "엽/叶",
    "엽/惗",
    "엽/曄",
    "엽/曅",
    "엽/熀",
    "엽/燁",
    "엽/爗",
    "엽/獵",
    "엽/葉"
  ],
  "영": [
    "영/䀴",
    "영/令",
    "영/伶",
    "영/呤",
    "영/咏",
    "영/嚀",
    "영/姈",
    "영/娙",
    "영/嬰",
    "영/嬴",
    "영/寗",
    "영/寧",
    "영/岭",
    "영/岺",
    "영/嶸",
    "영/嶺",
    "영/影",
    "영/怜",
    "영/映",
    "영/昤",
    "영/暎",
    "영/朠",
    "영/栄",
    "영/楹",
    "영/榮",
    "영/永",
    "영/泠",
    "영/泳",
    "영/浧",
    "영/渶",
    "영/潁",
    "영/澪",
    "영/濚",
    "영/濴",
    "영/瀛",
    "영/瀯",
    "영/煐",
    "영/營",
    "영/玲",
    "영/瑛",
    "영/瑩",
    "영/瓔",
    "영/盈",
    "영/碤",
    "영/穎",
    "영/縈",
    "영/羚",
    "영/翎",
    "영/聆",
    "영/英",
    "영/荣",
    "영/詠",
    "영/贏",
    "영/迎",
    "영/逞",
    "영/郢",
    "영/鈴",
    "영/鍈",
    "영/零",
    "영/霙",
    "영/靈",
    "영/韺",
    "영/領",
    "영/鹷",
    "영/齡"
  ],
  "예": [
    "예/㙯",
    "예/䜭",
    "예/䢃",
    "예/乂",
    "예/例",
    "예/兒",
    "예/列",
    "예/叡",
    "예/埶",
    "예/壡",
    "예/嫕",
    "예/帠",
    "예/掜",
    "예/曳",
    "예/枘",
    "예/橤",
    "예/汭",
    "예/澧",
    "예/獩",
    "예/玴",
    "예/瘱",
    "예/睿",
    "예/礼",
    "예/禮",
    "예/縘",
    "예/羿",
    "예/艾",
    "예/芮",
    "예/芸",
    "예/蓺",
    "예/蕊",
    "예/藝",
    "예/蘂",
    "예/蜺",
    "예/裔",
    "예/詣",
    "예/譽",
    "예/豫",
    "예/郳",
    "예/醴",
    "예/銳",
    "예/銴",
    "예/霓",
    "예/預",
    "예/麑"
  ],
  "오": [
    "오/䫨",
    "오/五",
    "오/伍",
    "오/俉",
    "오/午",
    "오/吳",
    "오/吾",
    "오/唔",
    "오/塢",
    "오/奧",
    "오/娛",
    "오/悟",
    "오/旿",
    "오/晤",
    "오/梧",
    "오/浯",
    "오/澳",
    "오/燠",
    "오/獒",
    "오/珸",
    "오/迕",
    "오/遨",
    "오/隩",
    "오/驁"
  ],
  "옥": [
    "옥/屋",
    "옥/沃",
    "옥/玉",
    "옥/鈺"
  ],
  "온": [
    "온/昷",
    "온/榲",
    "온/氳",
    "온/溫",
    "온/熅",
    "온/瑥",
    "온/稳",
    "온/穩",
    "온/蘊",
    "온/醞",
    "온/馧"
  ],
  "올": [
    "올/榲"
  ],
  "와": [
    "와/鮭"
  ],
  "완": [
    "완/垸",
    "완/妧",
    "완/婉",
    "완/婠",
    "완/完",
    "완/宛",
    "완/抏",
    "완/杬",
    "완/梡",
    "완/椀",
    "완/涴",
    "완/琓",
    "완/琬",
    "완/碗",
    "완/緩",
    "완/莞",
    "완/鋺",
    "완/阮",
    "완/頑"
  ],
  "왕": [
    "왕/旺",
    "왕/汪",
    "왕/瀇",
    "왕/王"
  ],
  "외": [
    "외/偎",
    "외/外",
    "외/崴",
    "외/嵬",
    "외/巍",
    "외/隗"
  ],
  "요": [
    "요/偠",
    "요/僚",
    "요/堯",
    "요/姚",
    "요/嫋",
    "요/嫽",
    "요/寮",
    "요/嶢",
    "요/徭",
    "요/徼",
    "요/撩",
    "요/料",
    "요/暚",
    "요/暸",
    "요/曜",
    "요/樂",
    "요/潦",
    "요/澆",
    "요/燎",
    "요/燿",
    "요/瑤",
    "요/療",
    "요/瞭",
    "요/穾",
    "요/窅",
    "요/窈",
    "요/窯",
    "요/繇",
    "요/耀",
    "요/聊",
    "요/腰",
    "요/蓼",
    "요/要",
    "요/謠",
    "요/遶",
    "요/邀",
    "요/鐃",
    "요/饒",
    "요/鷂"
  ],
  "용": [
    "용/㦶",
    "용/傛",
    "용/勇",
    "용/埇",
    "용/墉",
    "용/容",
    "용/嵱",
    "용/庸",
    "용/慂",
    "용/榕",
    "용/槦",
    "용/涌",
    "용/湧",
    "용/溶",
    "용/熔",
    "용/瑢",
    "용/用",
    "용/甬",
    "용/竜",
    "용/聳",
    "용/茸",
    "용/蓉",
    "용/踊",
    "용/踴",
    "용/鎔",
    "용/鏞",
    "용/龍",
    "용/龒"
  ],
  "우": [
    "우/㥥",
    "우/㲾",
    "우/䨒",
    "우/于",
    "우/亴",
    "우/佑",
    "우/俁",
    "우/優",
    "우/又",
    "우/友",
    "우/右",
    "우/宇",
    "우/寓",
    "우/尤",
    "우/嵎",
    "우/庽",
    "우/慪",
    "우/扜",
    "우/旴",
    "우/杅",
    "우/燠",
    "우/玗",
    "우/瑀",
    "우/甌",
    "우/盂",
    "우/盱",
    "우/祐",
    "우/禑",
    "우/禹",
    "우/竽",
    "우/羽",
    "우/耦",
    "우/耰",
    "우/芋",
    "우/藕",
    "우/遇",
    "우/邘",
    "우/郵",
    "우/釪",
    "우/鍝",
    "우/隅",
    "우/雨",
    "우/麀",
    "우/麌"
  ],
  "욱": [
    "욱/勖",
    "욱/圁",
    "욱/彧",
    "욱/旭",
    "욱/昱",
    "욱/栯",
    "욱/煜",
    "욱/燠",
    "욱/稢",
    "욱/稶",
    "욱/郁",
    "욱/頊"
  ],
  "운": [
    "운/䉙",
    "운/䫟",
    "운/云",
    "운/員",
    "운/均",
    "운/夽",
    "운/沄",
    "운/澐",
    "운/煇",
    "운/熉",
    "운/篔",
    "운/芸",
    "운/蕓",
    "운/賱",
    "운/運",
    "운/鄖",
    "운/雲",
    "운/韵",
    "운/韻"
  ],
  "웅": [
    "웅/熊"
  ],
  "원": [
    "원/倇",
    "원/元",
    "원/原",
    "원/員",
    "원/園",
    "원/圓",
    "원/圜",
    "원/垣",
    "원/婉",
    "원/媛",
    "원/嫄",
    "원/愿",
    "원/援",
    "원/杬",
    "원/沅",
    "원/洹",
    "원/湲",
    "원/源",
    "원/爰",
    "원/瑗",
    "원/笎",
    "원/芫",
    "원/苑",
    "원/薗",
    "원/袁",
    "원/褑",
    "원/謜",
    "원/貟",
    "원/遠",
    "원/邍",
    "원/鋺",
    "원/阮",
    "원/院",
    "원/願",
    "원/騵",
    "원/鴛",
    "원/鵷",
    "원/黿"
  ],
  "월": [
    "월/月",
    "월/粤",
    "월/越"
  ],
  "위": [
    "위/位",
    "위/偉",
    "위/圍",
    "위/委",
    "위/威",
    "위/尉",
    "위/幃",
    "위/暐",
    "위/渭",
    "위/爲",
    "위/瑋",
    "위/緯",
    "위/葳",
    "위/蔿",
    "위/衛",
    "위/衞",
    "위/褘",
    "위/謂",
    "위/闈",
    "위/韙",
    "위/韡",
    "위/餧",
    "위/魏"
  ],
  "유": [
    "유/㴗",
    "유/乳",
    "유/侑",
    "유/俞",
    "유/儒",
    "유/兪",
    "유/唯",
    "유/喩",
    "유/囿",
    "유/壝",
    "유/婑",
    "유/宥",
    "유/帷",
    "유/幽",
    "유/庾",
    "유/忸",
    "유/惟",
    "유/愈",
    "유/愉",
    "유/攸",
    "유/旒",
    "유/曘",
    "유/有",
    "유/柔",
    "유/柚",
    "유/柳",
    "유/楡",
    "유/楢",
    "유/榴",
    "유/橊",
    "유/洧",
    "유/流",
    "유/渷",
    "유/湵",
    "유/瀏",
    "유/琟",
    "유/瑈",
    "유/瑜",
    "유/瑠",
    "유/由",
    "유/留",
    "유/瘉",
    "유/秞",
    "유/籲",
    "유/紐",
    "유/聈",
    "유/臾",
    "유/萸",
    "유/蕤",
    "유/裕",
    "유/褕",
    "유/諭",
    "유/踰",
    "유/蹂",
    "유/逌",
    "유/逾",
    "유/遊",
    "유/遛",
    "유/遺",
    "유/釉",
    "유/鍮",
    "유/需",
    "유/鞣",
    "유/龥"
  ],
  "육": [
    "육/勠",
    "육/堉",
    "육/毓",
    "육/育",
    "육/陸"
  ],
  "윤": [
    "윤/㣧",
    "윤/䦞",
    "윤/倫",
    "윤/允",
    "윤/圇",
    "윤/奫",
    "윤/尹",
    "윤/崘",
    "윤/崙",
    "윤/掄",
    "윤/昀",
    "윤/橍",
    "윤/沇",
    "윤/潤",
    "윤/胤",
    "윤/荺",
    "윤/贇",
    "윤/輪",
    "윤/鈗",
    "윤/鋆",
    "윤/閏",
    "윤/閠",
    "윤/阭"
  ],
  "율": [
    "율/䢖",
    "율/䫻",
    "율/律",
    "율/栗",
    "율/汨",
    "율/汩",
    "율/溧",
    "율/潏",
    "율/燏",
    "율/率",
    "율/瑮",
    "율/聿",
    "율/鴥"
  ],
  "융": [
    "융/戎",
    "융/瀜",
    "융/癃",
    "융/絨",
    "융/融",
    "융/隆"
  ],
  "은": [
    "은/㒚",
    "은/听",
    "은/圁",
    "은/圻",
    "은/垠",
    "은/嶾",
    "은/恩",
    "은/檼",
    "은/殷",
    "은/溵",
    "은/濦",
    "은/珢",
    "은/蒑",
    "은/蒽",
    "은/蘟",
    "은/訢",
    "은/誾",
    "은/鄞",
    "은/銀"
  ],
  "을": [
    "을/乙",
    "을/鳦"
  ],
  "음": [
    "음/玪"
  ],
  "읍": [
    "읍/揖",
    "읍/邑"
  ],
  "응": [
    "응/應",
    "응/膺",
    "응/鷹"
  ],
  "의": [
    "의/㛄",
    "의/依",
    "의/倚",
    "의/儀",
    "의/儗",
    "의/凒",
    "의/宜",
    "의/嶷",
    "의/意",
    "의/懿",
    "의/擬",
    "의/椅",
    "의/毅",
    "의/漪",
    "의/矣",
    "의/礒",
    "의/義",
    "의/艤",
    "의/衣",
    "의/誼",
    "의/議",
    "의/醫"
  ],
  "이": [
    "이/㛅",
    "이/㦐",
    "이/二",
    "이/以",
    "이/伊",
    "이/佴",
    "이/俐",
    "이/利",
    "이/厘",
    "이/吏",
    "이/咿",
    "이/哩",
    "이/媐",
    "이/尔",
    "이/已",
    "이/巸",
    "이/廙",
    "이/彛",
    "이/彝",
    "이/怡",
    "이/悧",
    "이/摛",
    "이/易",
    "이/李",
    "이/柅",
    "이/栮",
    "이/梨",
    "이/浬",
    "이/涖",
    "이/漓",
    "이/濔",
    "이/犁",
    "이/犂",
    "이/狸",
    "이/珆",
    "이/理",
    "이/移",
    "이/籬",
    "이/羡",
    "이/而",
    "이/肄",
    "이/膩",
    "이/茸",
    "이/莅",
    "이/莉",
    "이/螭",
    "이/裏",
    "이/裡",
    "이/詑",
    "이/貳",
    "이/迤",
    "이/邇",
    "이/邐",
    "이/里",
    "이/釐",
    "이/馜",
    "이/鯉",
    "이/鴯",
    "이/黐"
  ],
  "익": [
    "익/瀷",
    "익/熤",
    "익/益",
    "익/翊",
    "익/翌",
    "익/翼",
    "익/謚",
    "익/鷁"
  ],
  "인": [
    "인/䗲",
    "인/人",
    "인/仁",
    "인/仞",
    "인/儿",
    "인/印",
    "인/吝",
    "인/因",
    "인/堙",
    "인/夤",
    "인/寅",
    "인/嶙",
    "인/引",
    "인/忈",
    "인/忍",
    "인/忎",
    "인/悋",
    "인/戭",
    "인/撛",
    "인/朄",
    "인/橉",
    "인/氤",
    "인/洇",
    "인/潾",
    "인/濥",
    "인/牣",
    "인/璌",
    "인/璘",
    "인/磷",
    "인/秵",
    "인/粼",
    "인/絪",
    "인/繗",
    "인/芢",
    "인/茵",
    "인/藺",
    "인/裀",
    "인/認",
    "인/諲",
    "인/鄰",
    "인/鏻",
    "인/隣",
    "인/靭",
    "인/韌",
    "인/麟"
  ],
  "일": [
    "일/一",
    "일/佚",
    "일/劮",
    "일/壹",
    "일/日",
    "일/昵",
    "일/昶",
    "일/暱",
    "일/溢",
    "일/軼",
    "일/逸",
    "일/鎰",
    "일/馹"
  ],
  "임": [
    "임/䚾",
    "임/䛘",
    "임/任",
    "임/壬",
    "임/恁",
    "임/晽",
    "임/林",
    "임/棽",
    "임/玪",
    "임/琳",
    "임/碄",
    "임/稔",
    "임/絍",
    "임/臨",
    "임/荏",
    "임/飪"
  ],
  "입": [
    "입/入",
    "입/岦",
    "입/立",
    "입/笠"
  ],
  "자": [
    "자/仔",
    "자/咨",
    "자/姉",
    "자/姊",
    "자/姿",
    "자/嬨",
    "자/子",
    "자/字",
    "자/孜",
    "자/孶",
    "자/恣",
    "자/慈",
    "자/柘",
    "자/泚",
    "자/滋",
    "자/牸",
    "자/玆",
    "자/磁",
    "자/粢",
    "자/耔",
    "자/自",
    "자/茲",
    "자/虸",
    "자/觜",
    "자/諮",
    "자/貲",
    "자/資",
    "자/鶿",
    "자/鷓"
  ],
  "작": [
    "작/乍"
  ],
  "장": [
    "장/丈",
    "장/仗",
    "장/匠",
    "장/場",
    "장/壮",
    "장/壯",
    "장/奘",
    "장/奬",
    "장/妝",
    "장/嬙",
    "장/将",
    "장/將",
    "장/嶂",
    "장/帳",
    "장/庄",
    "장/廧",
    "장/張",
    "장/掌",
    "장/暲",
    "장/樟",
    "장/檣",
    "장/欌",
    "장/漳",
    "장/牂",
    "장/狀",
    "장/獎",
    "장/璋",
    "장/章",
    "장/粧",
    "장/糚",
    "장/羘",
    "장/臧",
    "장/莊",
    "장/萇",
    "장/蔣",
    "장/薔",
    "장/裝",
    "장/鄣",
    "장/鏘",
    "장/長",
    "장/障"
  ],
  "재": [
    "재/再",
    "재/哉",
    "재/在",
    "재/夈",
    "재/宰",
    "재/崽",
    "재/才",
    "재/扗",
    "재/捚",
    "재/材",
    "재/栽",
    "재/榟",
    "재/渽",
    "재/溨",
    "재/纔",
    "재/財",
    "재/賳",
    "재/載",
    "재/齋",
    "재/齎"
  ],
  "전": [
    "전/佃",
    "전/佺",
    "전/傳",
    "전/全",
    "전/典",
    "전/囀",
    "전/塡",
    "전/嫥",
    "전/專",
    "전/展",
    "전/巓",
    "전/廛",
    "전/悛",
    "전/戩",
    "전/揃",
    "전/栴",
    "전/殿",
    "전/氈",
    "전/湔",
    "전/澶",
    "전/牋",
    "전/田",
    "전/甸",
    "전/畋",
    "전/畑",
    "전/痊",
    "전/筌",
    "전/箋",
    "전/篆",
    "전/籛",
    "전/腆",
    "전/荃",
    "전/詮",
    "전/躔",
    "전/轉",
    "전/鄽",
    "전/鈿",
    "전/銓",
    "전/鋑",
    "전/錢",
    "전/錪",
    "전/鐫",
    "전/雋",
    "전/電",
    "전/餞",
    "전/鱣",
    "전/鸇"
  ],
  "점": [
    "점/佔",
    "점/占",
    "점/岾",
    "점/店",
    "점/拈",
    "점/漸",
    "점/点",
    "점/粘",
    "점/蛅",
    "점/鮎",
    "점/黏",
    "점/點"
  ],
  "정": [
    "정/丁",
    "정/井",
    "정/亭",
    "정/侹",
    "정/停",
    "정/叮",
    "정/呈",
    "정/埩",
    "정/妌",
    "정/姃",
    "정/婧",
    "정/婷",
    "정/定",
    "정/庭",
    "정/廷",
    "정/征",
    "정/情",
    "정/挺",
    "정/掟",
    "정/政",
    "정/整",
    "정/旌",
    "정/晶",
    "정/晸",
    "정/柾",
    "정/桯",
    "정/棖",
    "정/楨",
    "정/檉",
    "정/正",
    "정/涏",
    "정/淨",
    "정/湞",
    "정/瀞",
    "정/炡",
    "정/玎",
    "정/珵",
    "정/珽",
    "정/眐",
    "정/睛",
    "정/碇",
    "정/禎",
    "정/程",
    "정/穽",
    "정/精",
    "정/胜",
    "정/艇",
    "정/莛",
    "정/訂",
    "정/証",
    "정/諪",
    "정/貞",
    "정/鄭",
    "정/鋌",
    "정/霆",
    "정/靖",
    "정/靘",
    "정/静",
    "정/靚",
    "정/靜",
    "정/頂",
    "정/頲",
    "정/鼎"
  ],
  "제": [
    "제/偙",
    "제/儕",
    "제/制",
    "제/劑",
    "제/堤",
    "제/姼",
    "제/媞",
    "제/帝",
    "제/弟",
    "제/悌",
    "제/晢",
    "제/済",
    "제/濟",
    "제/瑅",
    "제/禔",
    "제/第",
    "제/製",
    "제/諸",
    "제/躋",
    "제/醍",
    "제/鍗",
    "제/除",
    "제/隄",
    "제/題",
    "제/鮧",
    "제/鯷",
    "제/齊"
  ],
  "조": [
    "조/傮",
    "조/兆",
    "조/助",
    "조/噪",
    "조/嬥",
    "조/嶆",
    "조/彫",
    "조/找",
    "조/措",
    "조/操",
    "조/早",
    "조/昭",
    "조/晁",
    "조/曹",
    "조/曺",
    "조/朝",
    "조/枣",
    "조/棗",
    "조/漕",
    "조/潮",
    "조/照",
    "조/燥",
    "조/琱",
    "조/璪",
    "조/眺",
    "조/祖",
    "조/祚",
    "조/租",
    "조/稠",
    "조/窕",
    "조/笊",
    "조/組",
    "조/絩",
    "조/肇",
    "조/臊",
    "조/艚",
    "조/詔",
    "조/誂",
    "조/調",
    "조/趙",
    "조/造",
    "조/遭",
    "조/釣",
    "조/鈟",
    "조/銚",
    "조/雕",
    "조/鳥",
    "조/鵰",
    "조/鼂"
  ],
  "족": [
    "족/蔟"
  ],
  "종": [
    "종/倧",
    "종/宗",
    "종/從",
    "종/悰",
    "종/慒",
    "종/柊",
    "종/棕",
    "종/椶",
    "종/樅",
    "종/淙",
    "종/琮",
    "종/瑽",
    "종/種",
    "종/綜",
    "종/踪",
    "종/蹤",
    "종/鍾",
    "종/鐘"
  ],
  "좌": [
    "좌/佐",
    "좌/坐",
    "좌/左",
    "좌/座"
  ],
  "주": [
    "주/㫶",
    "주/䝬",
    "주/主",
    "주/住",
    "주/做",
    "주/儔",
    "주/冑",
    "주/周",
    "주/呪",
    "주/嗾",
    "주/奏",
    "주/妵",
    "주/姝",
    "주/宙",
    "주/州",
    "주/幬",
    "주/廚",
    "주/拄",
    "주/晝",
    "주/晭",
    "주/朱",
    "주/枓",
    "주/柱",
    "주/株",
    "주/椆",
    "주/檮",
    "주/洲",
    "주/湊",
    "주/澍",
    "주/炷",
    "주/燽",
    "주/珘",
    "주/珠",
    "주/疇",
    "주/皗",
    "주/硃",
    "주/籀",
    "주/籌",
    "주/紬",
    "주/紸",
    "주/絑",
    "주/綢",
    "주/腠",
    "주/舟",
    "주/蔟",
    "주/裯",
    "주/註",
    "주/調",
    "주/賙",
    "주/走",
    "주/趎",
    "주/輈",
    "주/輳",
    "주/週",
    "주/邾",
    "주/鉒",
    "주/鑄",
    "주/霌",
    "주/駐"
  ],
  "준": [
    "준/䜭",
    "준/俊",
    "준/僔",
    "준/儁",
    "준/准",
    "준/凖",
    "준/埈",
    "준/埻",
    "준/寯",
    "준/峻",
    "준/懏",
    "준/晙",
    "준/浚",
    "준/準",
    "준/濬",
    "준/畯",
    "준/睃",
    "준/竴",
    "준/純",
    "준/葰",
    "준/迿",
    "준/遵",
    "준/陖",
    "준/隼",
    "준/雋",
    "준/駿",
    "준/鱒",
    "준/鵔"
  ],
  "중": [
    "중/中",
    "중/仲",
    "중/眾",
    "중/衆",
    "중/重"
  ],
  "즙": [
    "즙/楫"
  ],
  "증": [
    "증/增",
    "증/嶒",
    "증/拯",
    "증/曾",
    "증/繒",
    "증/罾",
    "증/証",
    "증/證",
    "증/贈"
  ],
  "지": [
    "지/劧",
    "지/只",
    "지/地",
    "지/址",
    "지/坁",
    "지/坻",
    "지/墀",
    "지/媞",
    "지/志",
    "지/忯",
    "지/扺",
    "지/持",
    "지/指",
    "지/搘",
    "지/摯",
    "지/支",
    "지/旨",
    "지/智",
    "지/枝",
    "지/柴",
    "지/楫",
    "지/榰",
    "지/池",
    "지/汦",
    "지/泜",
    "지/洔",
    "지/漬",
    "지/知",
    "지/祇",
    "지/祉",
    "지/祗",
    "지/禔",
    "지/秖",
    "지/篪",
    "지/紙",
    "지/至",
    "지/芝",
    "지/芷",
    "지/觗",
    "지/誌",
    "지/識",
    "지/贄",
    "지/趾",
    "지/鋕",
    "지/阯",
    "지/馶",
    "지/鷙"
  ],
  "직": [
    "직/直",
    "직/禝",
    "직/稙",
    "직/織",
    "직/職"
  ],
  "진": [
    "진/䑐",
    "진/儘",
    "진/塡",
    "진/尽",
    "진/愼",
    "진/抮",
    "진/振",
    "진/敒",
    "진/昣",
    "진/晉",
    "진/晋",
    "진/枃",
    "진/槇",
    "진/殄",
    "진/津",
    "진/溱",
    "진/珍",
    "진/珒",
    "진/瑨",
    "진/璡",
    "진/畛",
    "진/盡",
    "진/眞",
    "진/真",
    "진/眹",
    "진/禛",
    "진/秦",
    "진/稹",
    "진/縉",
    "진/縝",
    "진/臻",
    "진/蓁",
    "진/蔯",
    "진/螴",
    "진/診",
    "진/賑",
    "진/辰",
    "진/進",
    "진/鉁",
    "진/鎭",
    "진/陣",
    "진/陳",
    "진/震",
    "진/靕"
  ],
  "집": [
    "집/什",
    "집/咠",
    "집/執",
    "집/戢",
    "집/楫",
    "집/潗",
    "집/緝",
    "집/輯",
    "집/集"
  ],
  "차": [
    "차/且",
    "차/佽",
    "차/叉",
    "차/奲",
    "차/姹",
    "차/岔",
    "차/嵯",
    "차/差",
    "차/次",
    "차/此",
    "차/瑳",
    "차/硨",
    "차/磋",
    "차/茶",
    "차/車",
    "차/鹺"
  ],
  "착": [
    "착/蔟"
  ],
  "찬": [
    "찬/㜺",
    "찬/儧",
    "찬/儹",
    "찬/巑",
    "찬/撮",
    "찬/撰",
    "찬/攢",
    "찬/欑",
    "찬/澯",
    "찬/燦",
    "찬/爨",
    "찬/璨",
    "찬/瓚",
    "찬/粲",
    "찬/纂",
    "찬/纘",
    "찬/讃",
    "찬/讚",
    "찬/賛",
    "찬/贊",
    "찬/餐"
  ],
  "참": [
    "참/參",
    "참/摻"
  ],
  "창": [
    "창/倉",
    "창/創",
    "창/唱",
    "창/廠",
    "창/彰",
    "창/搶",
    "창/敞",
    "창/昌",
    "창/昶",
    "창/晿",
    "창/暢",
    "창/槍",
    "창/淌",
    "창/淐",
    "창/滄",
    "창/漲",
    "창/瑲",
    "창/窓",
    "창/窗",
    "창/脹",
    "창/艙",
    "창/菖",
    "창/蒼",
    "창/鋹",
    "창/閶",
    "창/鬯",
    "창/鶬"
  ],
  "채": [
    "채/埰",
    "채/婇",
    "채/寀",
    "채/寨",
    "채/彩",
    "채/採",
    "채/撮",
    "채/柴",
    "채/棌",
    "채/琗",
    "채/睬",
    "채/砦",
    "채/綵",
    "채/茝",
    "채/菜",
    "채/蔡",
    "채/采"
  ],
  "천": [
    "천/仟",
    "천/俴",
    "천/倩",
    "천/千",
    "천/天",
    "천/川",
    "천/泉",
    "천/洊",
    "천/淺",
    "천/濺",
    "천/玔",
    "천/祆",
    "천/穿",
    "천/臶",
    "천/芊",
    "천/荐",
    "천/蔳",
    "천/蕆",
    "천/薦",
    "천/辿",
    "천/遷",
    "천/釧",
    "천/闡",
    "천/阡",
    "천/靝",
    "천/韆"
  ],
  "철": [
    "철/哲",
    "철/啜",
    "철/喆",
    "철/埑",
    "철/徹",
    "철/悊",
    "철/掇",
    "철/撤",
    "철/歠",
    "철/澈",
    "철/瞮",
    "철/綴",
    "철/輟",
    "철/鉄",
    "철/銕",
    "철/錣",
    "철/鐵"
  ],
  "첨": [
    "첨/諶"
  ],
  "청": [
    "청/凊",
    "청/婧",
    "청/廳",
    "청/晴",
    "청/淸",
    "청/清",
    "청/聽",
    "청/菁",
    "청/請",
    "청/靑",
    "청/青",
    "청/鶄"
  ],
  "체": [
    "체/銴"
  ],
  "초": [
    "초/俏",
    "초/僬",
    "초/初",
    "초/哨",
    "초/噍",
    "초/岧",
    "초/峭",
    "초/嶕",
    "초/抄",
    "초/招",
    "초/杪",
    "초/椒",
    "초/楚",
    "초/樵",
    "초/硝",
    "초/礎",
    "초/稍",
    "초/綃",
    "초/耖",
    "초/肖",
    "초/艸",
    "초/苕",
    "초/草",
    "초/超",
    "초/趠",
    "초/軺",
    "초/迢",
    "초/釥",
    "초/鍫",
    "초/鍬"
  ],
  "촉": [
    "촉/數"
  ],
  "촌": [
    "촌/吋",
    "촌/寸",
    "촌/忖",
    "촌/村",
    "촌/邨"
  ],
  "촬": [
    "촬/撮"
  ],
  "최": [
    "최/催",
    "최/崔",
    "최/摧",
    "최/撮",
    "최/最",
    "최/榱",
    "최/漼",
    "최/璀",
    "최/磪"
  ],
  "추": [
    "추/䆋",
    "추/僦",
    "추/墜",
    "추/娵",
    "추/抽",
    "추/推",
    "추/揫",
    "추/椎",
    "추/楸",
    "추/樞",
    "추/湫",
    "추/瘳",
    "추/秋",
    "추/芻",
    "추/萩",
    "추/蒭",
    "추/諏",
    "추/鄒",
    "추/酋",
    "추/錐",
    "추/錘",
    "추/鎚",
    "추/陬",
    "추/隧",
    "추/隹",
    "추/騅",
    "추/鵻",
    "추/鶖",
    "추/麤"
  ],
  "춘": [
    "춘/春",
    "춘/椿",
    "춘/瑃",
    "춘/胊",
    "춘/賰"
  ],
  "출": [
    "출/出",
    "출/朮",
    "출/秫"
  ],
  "충": [
    "충/充",
    "충/冲",
    "충/忠",
    "충/沖",
    "충/珫",
    "충/衷"
  ],
  "치": [
    "치/値",
    "치/卮",
    "치/哆",
    "치/塡",
    "치/寘",
    "치/峙",
    "치/幟",
    "치/柴",
    "치/梔",
    "치/治",
    "치/淄",
    "치/熾",
    "치/純",
    "치/絺",
    "치/緇",
    "치/緻",
    "치/置",
    "치/致",
    "치/薙",
    "치/跱",
    "치/輜",
    "치/錙",
    "치/阤",
    "치/馳",
    "치/鯔",
    "치/齒"
  ],
  "칠": [
    "칠/七"
  ],
  "타": [
    "타/媞"
  ],
  "탁": [
    "탁/倬",
    "탁/卓",
    "탁/坼",
    "탁/度",
    "탁/托",
    "탁/拓",
    "탁/擢",
    "탁/晫",
    "탁/棹",
    "탁/槖",
    "탁/橐",
    "탁/澤",
    "탁/琢",
    "탁/琸",
    "탁/矺",
    "탁/籜",
    "탁/託",
    "탁/踔",
    "탁/逴",
    "탁/鐸"
  ],
  "탄": [
    "탄/妲"
  ],
  "탈": [
    "탈/說"
  ],
  "태": [
    "태/兌",
    "태/台",
    "태/埭",
    "태/太",
    "태/娧",
    "태/媞",
    "태/態",
    "태/汏",
    "태/汰",
    "태/泰",
    "태/珆",
    "태/脫",
    "태/迨",
    "태/邰",
    "태/颱",
    "태/駘",
    "태/鮐"
  ],
  "택": [
    "택/垞",
    "택/宅",
    "택/擇",
    "택/澤"
  ],
  "퇴": [
    "퇴/推"
  ],
  "파": [
    "파/坡",
    "파/妑",
    "파/岥",
    "파/搫",
    "파/播",
    "파/擺",
    "파/杷",
    "파/波",
    "파/派",
    "파/灞",
    "파/玻",
    "파/琶",
    "파/芭",
    "파/葩",
    "파/鄱",
    "파/頗"
  ],
  "판": [
    "판/判",
    "판/坂",
    "판/弁",
    "판/瓣",
    "판/辦",
    "판/阪"
  ],
  "팔": [
    "팔/八",
    "팔/叭",
    "팔/朳",
    "팔/汃"
  ],
  "팽": [
    "팽/彭",
    "팽/旁"
  ],
  "편": [
    "편/便"
  ],
  "평": [
    "평/坪",
    "평/平",
    "평/怦",
    "평/枰",
    "평/泙",
    "평/萍",
    "평/評"
  ],
  "폐": [
    "폐/蘗",
    "폐/銴"
  ],
  "표": [
    "표/俵",
    "표/僄",
    "표/勡",
    "표/嘌",
    "표/彪",
    "표/標",
    "표/票",
    "표/縹",
    "표/裱",
    "표/豹",
    "표/髟"
  ],
  "풍": [
    "풍/楓",
    "풍/諷",
    "풍/豊",
    "풍/豐",
    "풍/風",
    "풍/馮"
  ],
  "필": [
    "필/㪤",
    "필/㳼",
    "필/佖",
    "필/咇",
    "필/弼",
    "필/必",
    "필/泌",
    "필/滭",
    "필/筆",
    "필/苾",
    "필/蓽",
    "필/觱",
    "필/蹕",
    "필/馝",
    "필/駜"
  ],
  "하": [
    "하/㗿",
    "하/㰤",
    "하/何",
    "하/嘏",
    "하/嚇",
    "하/夏",
    "하/岈",
    "하/抲",
    "하/河",
    "하/芐",
    "하/蕸",
    "하/賀",
    "하/赮",
    "하/遐",
    "하/閜",
    "하/霞"
  ],
  "학": [
    "학/壑",
    "학/学",
    "학/學",
    "학/皬",
    "학/郝",
    "학/鄗",
    "학/鶴",
    "학/鷽"
  ],
  "한": [
    "한/䦥",
    "한/僩",
    "한/嫺",
    "한/嫻",
    "한/忓",
    "한/扞",
    "한/捍",
    "한/橌",
    "한/漢",
    "한/澖",
    "한/澣",
    "한/瀚",
    "한/罕",
    "한/翰",
    "한/邗",
    "한/閈",
    "한/閑",
    "한/閒",
    "한/韓",
    "한/鷳"
  ],
  "함": [
    "함/函",
    "함/含",
    "함/咸",
    "함/喊",
    "함/檻",
    "함/緘",
    "함/艦",
    "함/莟",
    "함/菡",
    "함/諴",
    "함/闞"
  ],
  "항": [
    "항/亢",
    "항/夯",
    "항/姮",
    "항/嫦",
    "항/巷",
    "항/恆",
    "항/恒",
    "항/抗",
    "항/杭",
    "항/沆",
    "항/港",
    "항/缸",
    "항/航",
    "항/行",
    "항/項",
    "항/頏"
  ],
  "해": [
    "해/偕",
    "해/垓",
    "해/奚",
    "해/嶰",
    "해/晐",
    "해/楷",
    "해/海",
    "해/澥",
    "해/瀣",
    "해/獬",
    "해/瑎",
    "해/祄",
    "해/薤",
    "해/解",
    "해/該",
    "해/諧",
    "해/邂",
    "해/鮭"
  ],
  "행": [
    "행/幸",
    "행/杏",
    "행/涬",
    "행/荇",
    "행/行"
  ],
  "향": [
    "향/享",
    "향/向",
    "향/嚮",
    "향/晑",
    "향/珦",
    "향/薌",
    "향/鄕",
    "향/響",
    "향/餉",
    "향/饗",
    "향/香",
    "향/麘"
  ],
  "허": [
    "허/墟",
    "허/許"
  ],
  "헌": [
    "헌/㦥",
    "헌/巚",
    "헌/幰",
    "헌/憲",
    "헌/攇",
    "헌/昍",
    "헌/櫶",
    "헌/獻",
    "헌/瓛",
    "헌/軒"
  ],
  "혁": [
    "혁/侐",
    "혁/嚇",
    "혁/奕",
    "혁/弈",
    "혁/焃",
    "혁/焱",
    "혁/爀",
    "혁/赫"
  ],
  "현": [
    "현/㢺",
    "현/㭹",
    "현/䧋",
    "현/儇",
    "현/呟",
    "현/夐",
    "현/妶",
    "현/娊",
    "현/嬛",
    "현/峴",
    "현/昡",
    "현/晛",
    "현/泫",
    "현/灦",
    "현/炫",
    "현/玄",
    "현/玹",
    "현/現",
    "현/琄",
    "현/絃",
    "현/絢",
    "현/縣",
    "현/翾",
    "현/衒",
    "현/見",
    "현/譞",
    "현/賢",
    "현/鋗",
    "현/顕",
    "현/顯"
  ],
  "협": [
    "협/俠",
    "협/冾",
    "협/匧",
    "협/協",
    "협/叶",
    "협/埉",
    "협/峽",
    "협/恊",
    "협/悏",
    "협/愜",
    "협/浹",
    "협/篋",
    "협/鋏"
  ],
  "형": [
    "형/亨",
    "형/兄",
    "형/型",
    "형/夐",
    "형/娙",
    "형/形",
    "형/泂",
    "형/滎",
    "형/瀅",
    "형/灐",
    "형/炯",
    "형/熒",
    "형/瑩",
    "형/荊",
    "형/螢",
    "형/衡",
    "형/迥",
    "형/逈",
    "형/邢",
    "형/陘",
    "형/馨"
  ],
  "혜": [
    "혜/䚷",
    "혜/兮",
    "혜/嘒",
    "혜/寭",
    "혜/彗",
    "혜/徯",
    "혜/恵",
    "혜/惠",
    "혜/慧",
    "혜/憓",
    "혜/暳",
    "혜/蕙",
    "혜/譓",
    "혜/譿",
    "혜/醯",
    "혜/鏸"
  ],
  "호": [
    "호/乎",
    "호/互",
    "호/儫",
    "호/号",
    "호/呼",
    "호/壕",
    "호/壺",
    "호/好",
    "호/婋",
    "호/嫭",
    "호/嫮",
    "호/岵",
    "호/弧",
    "호/怙",
    "호/戶",
    "호/扈",
    "호/昊",
    "호/晧",
    "호/浩",
    "호/淏",
    "호/湖",
    "호/滈",
    "호/滬",
    "호/滸",
    "호/澔",
    "호/濠",
    "호/濩",
    "호/灝",
    "호/熩",
    "호/犒",
    "호/琥",
    "호/瑚",
    "호/皓",
    "호/皜",
    "호/皞",
    "호/祜",
    "호/縞",
    "호/翺",
    "호/聕",
    "호/芐",
    "호/芦",
    "호/蒿",
    "호/蔰",
    "호/虎",
    "호/號",
    "호/謼",
    "호/護",
    "호/豪",
    "호/鄗",
    "호/鎬",
    "호/頀",
    "호/顥"
  ],
  "혹": [
    "혹/歊"
  ],
  "혼": [
    "혼/煇",
    "혼/緄"
  ],
  "홍": [
    "홍/哄",
    "홍/弘",
    "홍/晎",
    "홍/泓",
    "홍/洪",
    "홍/澒",
    "홍/篊",
    "홍/紅",
    "홍/虹",
    "홍/鉷",
    "홍/鴻"
  ],
  "화": [
    "화/俰",
    "화/化",
    "화/和",
    "화/嬅",
    "화/樺",
    "화/澕",
    "화/火",
    "화/畫",
    "화/畵",
    "화/禾",
    "화/花",
    "화/華",
    "화/話",
    "화/貨",
    "화/靴",
    "화/驊",
    "화/鮭",
    "화/龢"
  ],
  "환": [
    "환/丸",
    "환/喚",
    "환/圜",
    "환/奐",
    "환/嬛",
    "환/宦",
    "환/寰",
    "환/懽",
    "환/換",
    "환/擐",
    "환/晥",
    "환/桓",
    "환/歡",
    "환/洹",
    "환/渙",
    "환/煥",
    "환/環",
    "환/瓛",
    "환/皖",
    "환/睆",
    "환/紈",
    "환/絙",
    "환/豢",
    "환/還",
    "환/鍰",
    "환/鐶",
    "환/驩",
    "환/鰥"
  ],
  "황": [
    "황/凰",
    "황/媓",
    "황/幌",
    "황/怳",
    "황/恍",
    "황/愰",
    "황/慌",
    "황/晃",
    "황/晄",
    "황/楻",
    "황/榥",
    "황/況",
    "황/湟",
    "황/滉",
    "황/煌",
    "황/熀",
    "황/瑝",
    "황/璜",
    "황/皇",
    "황/篁",
    "황/簧",
    "황/貺",
    "황/遑",
    "황/鎤",
    "황/隍",
    "황/黃"
  ],
  "회": [
    "회/会",
    "회/佪",
    "회/匯",
    "회/回",
    "회/廻",
    "회/恢",
    "회/懷",
    "회/晦",
    "회/會",
    "회/檜",
    "회/洄",
    "회/淮",
    "회/澮",
    "회/盔",
    "회/絵",
    "회/繪",
    "회/茴",
    "회/誨",
    "회/迴",
    "회/頮"
  ],
  "효": [
    "효/傚",
    "효/効",
    "효/嘐",
    "효/婋",
    "효/孝",
    "효/崤",
    "효/庨",
    "효/效",
    "효/斅",
    "효/曉",
    "효/歊",
    "효/殽",
    "효/洨",
    "효/涍",
    "효/淆",
    "효/烋",
    "효/熇",
    "효/爻",
    "효/皛",
    "효/窙",
    "효/謼",
    "효/酵",
    "효/餚",
    "효/驍"
  ],
  "후": [
    "후/㰭",
    "후/侯",
    "후/候",
    "후/厚",
    "후/后",
    "후/嗅",
    "후/垕",
    "후/堠",
    "후/姁",
    "후/帿",
    "후/後",
    "후/煦",
    "후/珝",
    "후/篌",
    "후/胊",
    "후/芋",
    "후/詡",
    "후/逅",
    "후/餱"
  ],
  "훈": [
    "훈/勛",
    "훈/勲",
    "훈/勳",
    "훈/塤",
    "훈/壎",
    "훈/暈",
    "훈/暉",
    "훈/曛",
    "훈/焄",
    "훈/煇",
    "훈/熏",
    "훈/燻",
    "훈/纁",
    "훈/葷",
    "훈/薫",
    "훈/薰",
    "훈/訓",
    "훈/鑂"
  ],
  "훤": [
    "훤/愃",
    "훤/昍",
    "훤/煇"
  ],
  "휘": [
    "휘/彙",
    "휘/徽",
    "휘/揮",
    "휘/暉",
    "휘/煇",
    "휘/煒",
    "휘/翬",
    "휘/輝",
    "휘/麾"
  ],
  "휴": [
    "휴/休",
    "휴/庥",
    "휴/携",
    "휴/烋",
    "휴/畦",
    "휴/隳",
    "휴/髤",
    "휴/鵂"
  ],
  "흔": [
    "흔/忻",
    "흔/惞",
    "흔/掀",
    "흔/昕",
    "흔/欣",
    "흔/痕"
  ],
  "흘": [
    "흘/汽"
  ],
  "흠": [
    "흠/廞",
    "흠/欽",
    "흠/鑫"
  ],
  "흥": [
    "흥/興"
  ],
  "희": [
    "희/㜯",
    "희/俙",
    "희/僖",
    "희/凞",
    "희/唏",
    "희/喜",
    "희/嘻",
    "희/囍",
    "희/姫",
    "희/姬",
    "희/嬉",
    "희/希",
    "희/悕",
    "희/憘",
    "희/憙",
    "희/戲",
    "희/晞",
    "희/暿",
    "희/曦",
    "희/橲",
    "희/烯",
    "희/煕",
    "희/熈",
    "희/熙",
    "희/熹",
    "희/熺",
    "희/爔",
    "희/犧",
    "희/禧",
    "희/稀",
    "희/羲",
    "희/譆",
    "희/豨",
    "희/餼"
  ]
}